tmotor_can_mit_mode/__init__.py
tmotor_can_mit_mode/channel_config.py
tmotor_can_mit_mode/tmotorCAN.py
tmotor_can_mit_mode-1.1.2.dist-info/LICENSE
tmotor_can_mit_mode-1.1.2.dist-info/METADATA
tmotor_can_mit_mode-1.1.2.dist-info/WHEEL
tmotor_can_mit_mode-1.1.2.dist-info/top_level.txt
tmotor_can_mit_mode-1.1.2.dist-info/RECORD
