Metadata-Version: 2.1
Name: tmotor_can_mit_mode
Version: 1.1.2
Summary: Package to control tmotor motors using CAN protocol
Author-email: Haricharan B <haricharan12122003@gmail.com>
Classifier: Programming Language :: Python :: 3
Classifier: License :: OSI Approved :: MIT License
Classifier: Operating System :: OS Independent
Requires-Python: >=3.7
License-File: LICENSE
